traktexport/__init__.py
traktexport/__main__.py
traktexport/dal.py
traktexport/export.py
traktexport/merge.py
traktexport/py.typed
traktexport-0.1.10.dist-info/LICENSE
traktexport-0.1.10.dist-info/METADATA
traktexport-0.1.10.dist-info/WHEEL
traktexport-0.1.10.dist-info/entry_points.txt
traktexport-0.1.10.dist-info/top_level.txt
traktexport-0.1.10.dist-info/RECORD
