Metadata-Version: 2.2
Name: traktexport
Version: 0.1.10
Summary: Export your Movies, TV shows and ratings from Trakt.tv
Home-page: https://github.com/purarue/traktexport
Author: purarue
License: MIT
Keywords: media movies export data
Classifier: License :: OSI Approved :: MIT License
Classifier: Programming Language :: Python
Classifier: Programming Language :: Python :: 3
Classifier: Programming Language :: Python :: 3 :: Only
Classifier: Programming Language :: Python :: 3.8
Classifier: Programming Language :: Python :: 3.9
Classifier: Programming Language :: Python :: 3.10
Classifier: Programming Language :: Python :: 3.11
Classifier: Programming Language :: Python :: 3.12
Requires-Python: >=3.8
License-File: LICENSE
Requires-Dist: IPython
Requires-Dist: backoff
Requires-Dist: click>=8.1
Requires-Dist: logzero
Requires-Dist: pytrakt>=4.1.0
Provides-Extra: testing
Requires-Dist: flake8; extra == "testing"
Requires-Dist: mypy; extra == "testing"
Requires-Dist: pytest; extra == "testing"
